deploynow-1.10.0.data/scripts/deploynow
src/__init__.py
src/__main__.py
src/color.py
src/deploynow.py
deploynow-1.10.0.dist-info/LICENSE
deploynow-1.10.0.dist-info/METADATA
deploynow-1.10.0.dist-info/WHEEL
deploynow-1.10.0.dist-info/top_level.txt
deploynow-1.10.0.dist-info/RECORD
